{"hash":"8fba78f9c40800590389de78ba655e341a14b70b","data":{"tag":{"title":"vue","belongsTo":{"totalCount":2,"pageInfo":{"totalPages":1,"currentPage":1},"edges":[{"node":{"title":"몇 명 정도 뽑으실 예정인가요?","timeToRead":1,"date":"March 14, 2020","path":"/question-number-five","summary":"12명입니다.","tags":[{"title":"frontend"},{"title":"coding"},{"title":"vue"}]}},{"node":{"title":"회비가 있나요?","timeToRead":1,"date":"March 13, 2020","path":"/question-number-seven","summary":"학교 회비로 5만원을 걷을 예정입니다.","tags":[{"title":"frontend"},{"title":"coding"},{"title":"vue"}]}}]}}},"context":{}}